banksync/__init__.py
banksync/banksync.py
banksync/banksync_common.py
banksync-0.9.10.data/scripts/bank
banksync-0.9.10.data/scripts/banksync
banksync-0.9.10.dist-info/LICENSE.txt
banksync-0.9.10.dist-info/METADATA
banksync-0.9.10.dist-info/WHEEL
banksync-0.9.10.dist-info/top_level.txt
banksync-0.9.10.dist-info/RECORD
