Metadata-Version: 2.1
Name: banksync
Version: 0.9.10
Summary: A library for manipulating banks of git repositories
Home-page: https://github.com/jasonfharris/banksync
Download-URL: https://github.com/jasonfharris/banksync/tarball/0.9.10
Author: Jason Harris
Author-email: jason@jasonfharris.com
License: MIT
Keywords: execute,shell,system,git,submodule
Classifier: Development Status :: 4 - Beta
Classifier: Intended Audience :: Developers
Classifier: Topic :: Software Development
Classifier: Topic :: Software Development :: Version Control
Classifier: Topic :: Utilities
Classifier: License :: OSI Approved :: MIT License
Classifier: Programming Language :: Python :: 2
Classifier: Programming Language :: Python :: 2.6
Classifier: Programming Language :: Python :: 2.7
Classifier: Programming Language :: Python :: 3.7
License-File: LICENSE.txt
Requires-Dist: argparse
Requires-Dist: argcomplete
Requires-Dist: sysexecute (>=1.1.6)
Requires-Dist: configparser
